starsol_fastapi_jwt_auth/__init__.py
starsol_fastapi_jwt_auth/auth_config.py
starsol_fastapi_jwt_auth/auth_jwt.py
starsol_fastapi_jwt_auth/config.py
starsol_fastapi_jwt_auth/exceptions.py
starsol_fastapi_jwt_auth-1.0.0.dist-info/LICENSE
starsol_fastapi_jwt_auth-1.0.0.dist-info/METADATA
starsol_fastapi_jwt_auth-1.0.0.dist-info/WHEEL
starsol_fastapi_jwt_auth-1.0.0.dist-info/top_level.txt
starsol_fastapi_jwt_auth-1.0.0.dist-info/RECORD
